navis-Ming-Qing_HarvYench_18_10_10092_0202-line-002-y1=111-y2=245-zone-HUMAN-x=0467-y=0034-w=0074-h=0072-ybas=0080-nink=1401-ns=1-segm=PERM4fwd <txt>@engl_assemble_pinyin_ji</txt> <utf> 96c6 </utf>
navis-Ming-Qing_HarvYench_18_10_10092_0202-line-002-y1=111-y2=245-zone-HUMAN-x=1415-y=0037-w=0071-h=0076-ybas=0080-nink=1380-segm=PERM1fwd <txt>@engl_gold_pinyin_jin</txt> <utf> 91d1 </utf>
navis-Ming-Qing_HarvYench_18_10_10092_0202-line-002-y1=111-y2=245-zone-HUMAN-x=1415-y=0037-w=0071-h=0076-ybas=0080-nink=1380-ns=1-segm=PERM4fwd <txt>@engl_gold_pinyin_jin</txt> <utf> 91d1 </utf>
navis-Ming-Qing_HarvYench_18_10_10092_0202-line-002-y1=111-y2=245-zone-HUMAN-x=1415-y=0037-w=0071-h=0076-ybas=0080-nink=1380-ns=1-segm=PERM4fwd <txt>@engl_gold_pinyin_jin</txt> <utf> 91d1 </utf>
navis-Ming-Qing_HarvYench_18_10_10092_0202-line-002-y1=111-y2=245-zone-HUMAN-x=1597-y=0041-w=0069-h=0074-ybas=0080-nink=1115-ns=1-segm=PERM4fwd <txt>@engl_king_pinyin_Wang</txt> <utf> 738B </utf>
navis-Ming-Qing_HarvYench_18_10_10092_0202-line-002-y1=111-y2=245-zone-HUMAN-x=1597-y=0041-w=0069-h=0074-ybas=0080-nink=1115-segm=PERM1fwd <txt>@engl_king_pinyin_Wang</txt> <utf> 738B </utf>
navis-Ming-Qing_HarvYench_18_10_10092_0202-line-002-y1=111-y2=245-zone-HUMAN-x=0656-y=0032-w=0074-h=0076-ybas=0080-nink=1210-ns=1-segm=PERM4fwd <txt>@engl_nine_pinyin_jiu</txt> <utf> 4e5d </utf>
navis-Ming-Qing_HarvYench_18_10_10092_0202-line-002-y1=111-y2=245-zone-HUMAN-x=0843-y=0034-w=0075-h=0075-ybas=0080-nink=1317-segm=PERM1fwd <txt>@engl_poem_pinyin_shi_traditional</txt> <utf> 8a69 </utf>
navis-Ming-Qing_HarvYench_18_10_10092_0202-line-002-y1=111-y2=245-zone-HUMAN-x=0940-y=0038-w=0068-h=0074-ybas=0080-nink=616-ns=3-segm=PERM4bck <txt>@engl_three_pinyin_san</txt> <utf> 4E09 </utf>
