navis-Ming-Qing_19686_0039-line-004-y1=328-y2=476-zone-HUMAN-x=2019-y=0014-w=0061-h=0087-ybas=0044-nink=1082-segm=PERM1fwd <txt>@engl_flutter_pinyin_pian</txt> <utf> 7fe9 </utf>
navis-Ming-Qing_19686_0039-line-004-y1=328-y2=476-zone-HUMAN-x=2019-y=0017-w=0061-h=0084-ybas=0044-nink=1022-segm=PERM1fwd <txt>@engl_flutter_pinyin_pian</txt> <utf> 7fe9 </utf>
navis-Ming-Qing_19686_0039-line-004-y1=328-y2=476-zone-HUMAN-x=2093-y=0011-w=0062-h=0093-ybas=0044-nink=1024-segm=PERM1fwd <txt>@engl_flutter_pinyin_pian</txt> <utf> 7fe9 </utf>
navis-Ming-Qing_19686_0039-line-004-y1=328-y2=476-zone-HUMAN-x=2093-y=0017-w=0062-h=0087-ybas=0044-nink=1004-segm=PERM1fwd <txt>@engl_flutter_pinyin_pian</txt> <utf> 7fe9 </utf>
navis-Ming-Qing_19686_0039-line-004-y1=328-y2=476-zone-HUMAN-x=0692-y=0014-w=0072-h=0088-ybas=0044-nink=1241-segm=PERM1fwd <txt>@engl_poplar_pinyin_yang_traditional</txt> <utf> 694a </utf>
navis-Ming-Qing_19686_0039-line-004-y1=328-y2=476-zone-HUMAN-x=0692-y=0017-w=0072-h=0085-ybas=0044-nink=1175-segm=PERM1fwd <txt>@engl_poplar_pinyin_yang_traditional</txt> <utf> 694a </utf>
navis-Ming-Qing_19686_0039-line-004-y1=328-y2=476-zone-HUMAN-x=1467-y=0004-w=0068-h=0091-ybas=0044-nink=918-segm=PERM1fwd <txt>@engl_rest_pinyin_xiu</txt> <utf> 4f11 </utf>
navis-Ming-Qing_19686_0039-line-004-y1=328-y2=476-zone-HUMAN-x=1467-y=0017-w=0068-h=0078-ybas=0044-nink=879-segm=PERM1fwd <txt>@engl_rest_pinyin_xiu</txt> <utf> 4f11 </utf>
navis-Ming-Qing_19686_0039-line-004-y1=328-y2=476-zone-HUMAN-x=2165-y=0010-w=0070-h=0081-ybas=0044-nink=872-segm=PERM1fwd <txt>@engl_serve_pinyin_shi_traditional</txt> <utf> 4f8d </utf>
navis-Ming-Qing_19686_0039-line-004-y1=328-y2=476-zone-HUMAN-x=2165-y=0017-w=0070-h=0074-ybas=0044-nink=810-segm=PERM1fwd <txt>@engl_serve_pinyin_shi_traditional</txt> <utf> 4f8d </utf>
navis-Ming-Qing_19686_0039-line-004-y1=328-y2=476-zone-HUMAN-x=0768-y=0009-w=0075-h=0095-ybas=0044-nink=1074-segm=PERM1fwd <txt>@engl_spring_pinyin_chun</txt> <utf> 6625 </utf>
navis-Ming-Qing_19686_0039-line-004-y1=328-y2=476-zone-HUMAN-x=0768-y=0017-w=0075-h=0087-ybas=0044-nink=1043-segm=PERM1fwd <txt>@engl_spring_pinyin_chun</txt> <utf> 6625 </utf>
navis-Ming-Qing_19686_0039-line-004-y1=328-y2=476-zone-HUMAN-x=1945-y=0015-w=0060-h=0074-ybas=0044-nink=703-segm=PERM1fwd <txt>@engl_sub_pinyin_zi</txt> <utf> 5b50 </utf>
navis-Ming-Qing_19686_0039-line-004-y1=328-y2=476-zone-HUMAN-x=1945-y=0017-w=0060-h=0072-ybas=0044-nink=676-segm=PERM1fwd <txt>@engl_sub_pinyin_zi</txt> <utf> 5b50 </utf>
navis-Ming-Qing_19686_0039-line-004-y1=328-y2=476-zone-HUMAN-x=0537-y=0010-w=0070-h=0093-ybas=0044-nink=1042-segm=PERM1fwd <txt>@engl_such_pinyin_qi</txt> <utf> 5176 </utf>
