navis-Ming-Qing_19686_0017-line-013-y1=1145-y2=1246-zone-HUMAN-x=0857-y=0030-w=0083-h=0054-ybas=0050-nink=790-segm=PERM1fwd <txt>@engl_clouds_pinyin_yun_traditional</txt> <utf> 96f2 </utf>
navis-Ming-Qing_19686_0017-line-013-y1=1145-y2=1246-zone-HUMAN-x=0857-y=0030-w=0083-h=0068-ybas=0050-nink=910-segm=PERM1fwd <txt>@engl_clouds_pinyin_yun_traditional</txt> <utf> 96f2 </utf>
navis-Ming-Qing_19686_0017-line-013-y1=1145-y2=1246-zone-HUMAN-x=0703-y=0031-w=0069-h=0053-ybas=0050-nink=838-segm=PERM1fwd <txt>@engl_difference_pinyin_cha</txt> <utf> 5dee </utf>
navis-Ming-Qing_19686_0017-line-013-y1=1145-y2=1246-zone-HUMAN-x=0703-y=0031-w=0069-h=0057-ybas=0050-nink=899-segm=PERM1fwd <txt>@engl_difference_pinyin_cha</txt> <utf> 5dee </utf>
navis-Ming-Qing_19686_0017-line-013-y1=1145-y2=1246-zone-HUMAN-x=1727-y=0015-w=0077-h=0066-ybas=0050-nink=1157-segm=PERM1fwd <txt>@engl_heavy_pinyin_zhong</txt> <utf> 91CD </utf>
navis-Ming-Qing_19686_0017-line-013-y1=1145-y2=1246-zone-HUMAN-x=1727-y=0017-w=0076-h=0064-ybas=0050-nink=966-segm=PERM1fwd <txt>@engl_heavy_pinyin_zhong</txt> <utf> 91CD </utf>
navis-Ming-Qing_19686_0017-line-013-y1=1145-y2=1246-zone-HUMAN-x=1005-y=0031-w=0083-h=0064-ybas=0050-nink=1147-segm=PERM1fwd <txt>@engl_leader_pinyin_shou</txt> <utf> 9996 </utf>
navis-Ming-Qing_19686_0017-line-013-y1=1145-y2=1246-zone-HUMAN-x=1557-y=0017-w=0076-h=0067-ybas=0050-nink=810-segm=PERM1fwd <txt>@engl_repeatedly_pinyin_fu</txt> <utf> 5fa9 </utf>
navis-Ming-Qing_19686_0017-line-013-y1=1145-y2=1246-zone-HUMAN-x=0628-y=0039-w=0071-h=0062-ybas=0050-nink=624-segm=PERM1fwd <txt>@engl_self_pinyin_zi</txt> <utf> 81ea </utf>
navis-Ming-Qing_19686_0017-line-013-y1=1145-y2=1246-zone-HUMAN-x=1178-y=0014-w=0063-h=0080-ybas=0050-nink=581-segm=PERM1fwd <txt>@engl_sky_pinyin_tian</txt> <utf> 5929 </utf>
navis-Ming-Qing_19686_0017-line-013-y1=1145-y2=1246-zone-HUMAN-x=1178-y=0017-w=0061-h=0067-ybas=0050-nink=484-segm=PERM1fwd <txt>@engl_sky_pinyin_tian</txt> <utf> 5929 </utf>
navis-Ming-Qing_19686_0017-line-013-y1=1145-y2=1246-zone-HUMAN-x=0788-y=0033-w=0060-h=0060-ybas=0050-nink=654-segm=PERM1fwd <txt>@engl_white_pinyin_bai</txt> <utf> 767d </utf>
navis-Ming-Qing_19686_0017-line-013-y1=1145-y2=1246-zone-HUMAN-x=1327-y=0008-w=0069-h=0089-ybas=0050-nink=822-segm=PERM1fwd <txt>@engl_without_pinyin_wu_traditional</txt> <utf> 7121 </utf>
navis-Ming-Qing_19686_0017-line-013-y1=1145-y2=1246-zone-HUMAN-x=1327-y=0017-w=0066-h=0067-ybas=0050-nink=719-segm=PERM1fwd <txt>@engl_without_pinyin_wu_traditional</txt> <utf> 7121 </utf>
