navis-Ming-Qing_HarvYench_18_10_10083_0050-line-004-y1=414-y2=542-zone-HUMAN-x=0923-y=0035-w=0069-h=0064-ybas=0063-nink=1003-segm=PERM1fwd <txt>@engl_sub_pinyin_zi</txt> <utf> 5b50 </utf>
navis-Ming-Qing_HarvYench_18_10_10083_0050-line-004-y1=414-y2=542-zone-HUMAN-x=1775-y=0024-w=0069-h=0072-ybas=0063-nink=1196-segm=PERM1fwd <txt>@engl_sub_pinyin_zi</txt> <utf> 5b50 </utf>
navis-Ming-Qing_HarvYench_18_10_10083_0050-line-004-y1=414-y2=542-zone-HUMAN-x=1987-y=0023-w=0071-h=0072-ybas=0063-nink=1055-segm=PERM1fwd <txt>@engl_sub_pinyin_zi</txt> <utf> 5b50 </utf>
