navis-Ming-Qing_19686_0009-line-004-y1=434-y2=575-zone-HUMAN-x=0232-y=0055-w=0101-h=0069-ybas=0061-nink=884-segm=PERM1fwd <txt>@engl_affair_pinyin_shi</txt> <utf> 4E8B </utf>
navis-Ming-Qing_19686_0009-line-004-y1=434-y2=575-zone-HUMAN-x=0232-y=0055-w=0101-h=0086-ybas=0061-nink=1065-segm=PERM1fwd <txt>@engl_affair_pinyin_shi</txt> <utf> 4E8B </utf>
navis-Ming-Qing_19686_0009-line-004-y1=434-y2=575-zone-HUMAN-x=1814-y=0017-w=0094-h=0073-ybas=0061-nink=1006-segm=PERM1fwd <txt>@engl_cyan_pinyin_qing</txt> <utf> 9752 </utf>
navis-Ming-Qing_19686_0009-line-004-y1=434-y2=575-zone-HUMAN-x=1814-y=0017-w=0094-h=0073-ybas=0061-nink=1081-segm=PERM1fwd <txt>@engl_cyan_pinyin_qing</txt> <utf> 9752 </utf>
navis-Ming-Qing_19686_0009-line-004-y1=434-y2=575-zone-HUMAN-x=2010-y=0012-w=0089-h=0103-ybas=0061-nink=1505-segm=PERM1fwd <txt>@engl_elegant_pinyin_ya</txt> <utf> 96c5 </utf>
navis-Ming-Qing_19686_0009-line-004-y1=434-y2=575-zone-HUMAN-x=2010-y=0017-w=0089-h=0098-ybas=0061-nink=1364-segm=PERM1fwd <txt>@engl_elegant_pinyin_ya</txt> <utf> 96c5 </utf>
navis-Ming-Qing_19686_0009-line-004-y1=434-y2=575-zone-HUMAN-x=1328-y=0035-w=0084-h=0084-ybas=0061-nink=1194-segm=PERM1fwd <txt>@engl_have_pinyin_you</txt> <utf> 6709 </utf>
navis-Ming-Qing_19686_0009-line-004-y1=434-y2=575-zone-HUMAN-x=1622-y=0022-w=0074-h=0066-ybas=0061-nink=880-segm=PERM1fwd <txt>@engl_still_pinyin_shang</txt> <utf> 5c1a </utf>
navis-Ming-Qing_19686_0009-line-004-y1=434-y2=575-zone-HUMAN-x=1622-y=0022-w=0077-h=0066-ybas=0061-nink=907-segm=PERM1fwd <txt>@engl_still_pinyin_shang</txt> <utf> 5c1a </utf>
navis-Ming-Qing_19686_0009-line-004-y1=434-y2=575-zone-HUMAN-x=1526-y=0031-w=0080-h=0093-ybas=0061-nink=1217-segm=PERM1fwd <txt>@engl_suffix_er_pinyin_zhe</txt> <utf> 8005 </utf>
navis-Ming-Qing_19686_0009-line-004-y1=434-y2=575-zone-HUMAN-x=1526-y=0031-w=0080-h=0096-ybas=0061-nink=1246-segm=PERM1fwd <txt>@engl_suffix_er_pinyin_zhe</txt> <utf> 8005 </utf>
navis-Ming-Qing_19686_0009-line-004-y1=434-y2=575-zone-HUMAN-x=1225-y=0009-w=0083-h=0085-ybas=0061-nink=1168-segm=PERM1fwd <txt>@engl_through_pinyin_cong_traditional</txt> <utf> 5f9e </utf>
navis-Ming-Qing_19686_0009-line-004-y1=434-y2=575-zone-HUMAN-x=1225-y=0017-w=0083-h=0077-ybas=0061-nink=1117-segm=PERM1fwd <txt>@engl_through_pinyin_cong_traditional</txt> <utf> 5f9e </utf>
navis-Ming-Qing_19686_0009-line-004-y1=434-y2=575-zone-HUMAN-x=0739-y=0025-w=0087-h=0099-ybas=0061-nink=873-segm=PERM1fwd <txt>@engl_yes_pinyin_shi</txt> <utf> 662f </utf>
navis-Ming-Qing_19686_0009-line-004-y1=434-y2=575-zone-HUMAN-x=0739-y=0025-w=0088-h=0105-ybas=0061-nink=922-segm=PERM1fwd <txt>@engl_yes_pinyin_shi</txt> <utf> 662f </utf>
