navis-Ming-Qing_19686_0056-line-002-y1=193-y2=343-zone-HUMAN-x=0259-y=0034-w=0077-h=0077-ybas=0055-nink=945-segm=PERM1fwd <txt>@engl_cyan_pinyin_qing</txt> <utf> 9752 </utf>
navis-Ming-Qing_19686_0056-line-002-y1=193-y2=343-zone-HUMAN-x=0259-y=0034-w=0077-h=0077-ybas=0055-nink=972-segm=PERM1fwd <txt>@engl_cyan_pinyin_qing</txt> <utf> 9752 </utf>
navis-Ming-Qing_19686_0056-line-002-y1=193-y2=343-zone-HUMAN-x=0259-y=0035-w=0077-h=0075-ybas=0055-nink=862-segm=PERM1fwd <txt>@engl_cyan_pinyin_qing</txt> <utf> 9752 </utf>
navis-Ming-Qing_19686_0056-line-002-y1=193-y2=343-zone-HUMAN-x=0110-y=0037-w=0078-h=0064-ybas=0055-nink=1022-segm=PERM1fwd <txt>@engl_high_pinyin_gao_traditional</txt> <utf> 9ad9 </utf>
navis-Ming-Qing_19686_0056-line-002-y1=193-y2=343-zone-HUMAN-x=0110-y=0037-w=0078-h=0064-ybas=0055-nink=1063-segm=PERM1fwd <txt>@engl_high_pinyin_gao_traditional</txt> <utf> 9ad9 </utf>
navis-Ming-Qing_19686_0056-line-002-y1=193-y2=343-zone-HUMAN-x=0111-y=0037-w=0077-h=0064-ybas=0055-nink=902-segm=PERM1fwd <txt>@engl_high_pinyin_gao_traditional</txt> <utf> 9ad9 </utf>
navis-Ming-Qing_19686_0056-line-002-y1=193-y2=343-zone-HUMAN-x=0496-y=0035-w=0070-h=0066-ybas=0055-nink=809-segm=PERM1fwd <txt>@engl_house_pinyin_wu</txt> <utf> 5c4b </utf>
navis-Ming-Qing_19686_0056-line-002-y1=193-y2=343-zone-HUMAN-x=0496-y=0035-w=0070-h=0076-ybas=0055-nink=919-segm=PERM1fwd <txt>@engl_house_pinyin_wu</txt> <utf> 5c4b </utf>
navis-Ming-Qing_19686_0056-line-002-y1=193-y2=343-zone-HUMAN-x=0496-y=0035-w=0070-h=0076-ybas=0055-nink=971-segm=PERM1fwd <txt>@engl_house_pinyin_wu</txt> <utf> 5c4b </utf>
navis-Ming-Qing_19686_0056-line-002-y1=193-y2=343-zone-HUMAN-x=0891-y=0011-w=0065-h=0090-ybas=0055-nink=983-segm=PERM1fwd <txt>@engl_reside_pinyin_she</txt> <utf> 820d </utf>
navis-Ming-Qing_19686_0056-line-002-y1=193-y2=343-zone-HUMAN-x=0891-y=0017-w=0065-h=0084-ybas=0055-nink=815-segm=PERM1fwd <txt>@engl_reside_pinyin_she</txt> <utf> 820d </utf>
navis-Ming-Qing_19686_0056-line-002-y1=193-y2=343-zone-HUMAN-x=0891-y=0017-w=0065-h=0084-ybas=0055-nink=893-segm=PERM1fwd <txt>@engl_reside_pinyin_she</txt> <utf> 820d </utf>
navis-Ming-Qing_19686_0056-line-002-y1=193-y2=343-zone-HUMAN-x=1121-y=0015-w=0077-h=0073-ybas=0055-nink=1260-segm=PERM1fwd <txt>@engl_rosy_clouds_pinyin_xia</txt> <utf> 971e </utf>
navis-Ming-Qing_19686_0056-line-002-y1=193-y2=343-zone-HUMAN-x=1121-y=0017-w=0075-h=0071-ybas=0055-nink=1048-segm=PERM1fwd <txt>@engl_rosy_clouds_pinyin_xia</txt> <utf> 971e </utf>
navis-Ming-Qing_19686_0056-line-002-y1=193-y2=343-zone-HUMAN-x=1121-y=0017-w=0075-h=0071-ybas=0055-nink=1188-segm=PERM1fwd <txt>@engl_rosy_clouds_pinyin_xia</txt> <utf> 971e </utf>
navis-Ming-Qing_19686_0056-line-002-y1=193-y2=343-zone-HUMAN-x=1510-y=0007-w=0077-h=0089-ybas=0055-nink=1204-segm=PERM1fwd <txt>@engl_spring_pinyin_chun</txt> <utf> 6625 </utf>
navis-Ming-Qing_19686_0056-line-002-y1=193-y2=343-zone-HUMAN-x=1510-y=0017-w=0077-h=0079-ybas=0055-nink=1010-segm=PERM1fwd <txt>@engl_spring_pinyin_chun</txt> <utf> 6625 </utf>
navis-Ming-Qing_19686_0056-line-002-y1=193-y2=343-zone-HUMAN-x=1510-y=0017-w=0077-h=0079-ybas=0055-nink=1122-segm=PERM1fwd <txt>@engl_spring_pinyin_chun</txt> <utf> 6625 </utf>
