navis-Ming-Qing_19686_0059-line-010-y1=1169-y2=1366-zone-HUMAN-x=2307-y=0046-w=0067-h=0092-ybas=0094-nink=807-segm=PERM1fwd <txt>@engl_combine_pinyin_he</txt> <utf> 5408 </utf>
navis-Ming-Qing_19686_0059-line-010-y1=1169-y2=1366-zone-HUMAN-x=2307-y=0046-w=0067-h=0093-ybas=0095-nink=899-segm=PERM1fwd <txt>@engl_combine_pinyin_he</txt> <utf> 5408 </utf>
navis-Ming-Qing_19686_0059-line-010-y1=1169-y2=1366-zone-HUMAN-x=2307-y=0046-w=0067-h=0093-ybas=0095-nink=946-segm=PERM1fwd <txt>@engl_combine_pinyin_he</txt> <utf> 5408 </utf>
navis-Ming-Qing_19686_0059-line-010-y1=1169-y2=1366-zone-HUMAN-x=0534-y=0074-w=0076-h=0070-ybas=0094-nink=1016-segm=PERM1fwd <txt>@engl_english_pinyin_ying</txt> <utf> 82f1 </utf>
navis-Ming-Qing_19686_0059-line-010-y1=1169-y2=1366-zone-HUMAN-x=0534-y=0074-w=0076-h=0070-ybas=0095-nink=1147-segm=PERM1fwd <txt>@engl_english_pinyin_ying</txt> <utf> 82f1 </utf>
navis-Ming-Qing_19686_0059-line-010-y1=1169-y2=1366-zone-HUMAN-x=0534-y=0074-w=0076-h=0070-ybas=0095-nink=1179-segm=PERM1fwd <txt>@engl_english_pinyin_ying</txt> <utf> 82f1 </utf>
navis-Ming-Qing_19686_0059-line-010-y1=1169-y2=1366-zone-HUMAN-x=1620-y=0071-w=0068-h=0085-ybas=0095-nink=1203-segm=PERM1fwd <txt>@engl_if_pinyin_ruo</txt> <utf> 82E5 </utf>
navis-Ming-Qing_19686_0059-line-010-y1=1169-y2=1366-zone-HUMAN-x=1620-y=0071-w=0068-h=0085-ybas=0095-nink=1251-segm=PERM1fwd <txt>@engl_if_pinyin_ruo</txt> <utf> 82E5 </utf>
navis-Ming-Qing_19686_0059-line-010-y1=1169-y2=1366-zone-HUMAN-x=1620-y=0072-w=0068-h=0084-ybas=0094-nink=1089-segm=PERM1fwd <txt>@engl_if_pinyin_ruo</txt> <utf> 82E5 </utf>
navis-Ming-Qing_19686_0059-line-010-y1=1169-y2=1366-zone-HUMAN-x=1154-y=0067-w=0076-h=0097-ybas=0094-nink=1016-segm=PERM1fwd <txt>@engl_mansion_pinyin_sha</txt> <utf> 53a6 </utf>
navis-Ming-Qing_19686_0059-line-010-y1=1169-y2=1366-zone-HUMAN-x=1154-y=0067-w=0076-h=0097-ybas=0095-nink=1156-segm=PERM1fwd <txt>@engl_mansion_pinyin_sha</txt> <utf> 53a6 </utf>
navis-Ming-Qing_19686_0059-line-010-y1=1169-y2=1366-zone-HUMAN-x=1154-y=0067-w=0076-h=0097-ybas=0095-nink=1206-segm=PERM1fwd <txt>@engl_mansion_pinyin_sha</txt> <utf> 53a6 </utf>
navis-Ming-Qing_19686_0059-line-010-y1=1169-y2=1366-zone-HUMAN-x=1848-y=0059-w=0087-h=0084-ybas=0094-nink=1131-segm=PERM1fwd <txt>@engl_middle_pinyin_zhong</txt> <utf> 4e2d </utf>
navis-Ming-Qing_19686_0059-line-010-y1=1169-y2=1366-zone-HUMAN-x=1848-y=0059-w=0087-h=0084-ybas=0095-nink=1262-segm=PERM1fwd <txt>@engl_middle_pinyin_zhong</txt> <utf> 4e2d </utf>
navis-Ming-Qing_19686_0059-line-010-y1=1169-y2=1366-zone-HUMAN-x=1848-y=0059-w=0087-h=0084-ybas=0095-nink=1327-segm=PERM1fwd <txt>@engl_middle_pinyin_zhong</txt> <utf> 4e2d </utf>
