navis-Ming-Qing_19686_0038-line-007-y1=1227-y2=1373-zone-HUMAN-x=1042-y=0065-w=0065-h=0064-ybas=0096-nink=737-segm=PERM1fwd <txt>@engl_answer_pinyin_da</txt> <utf> 7b54 </utf>
navis-Ming-Qing_19686_0038-line-007-y1=1227-y2=1373-zone-HUMAN-x=1042-y=0065-w=0066-h=0064-ybas=0096-nink=823-segm=PERM1fwd <txt>@engl_answer_pinyin_da</txt> <utf> 7b54 </utf>
navis-Ming-Qing_19686_0038-line-007-y1=1227-y2=1373-zone-HUMAN-x=1042-y=0065-w=0066-h=0081-ybas=0096-nink=949-segm=PERM1fwd <txt>@engl_answer_pinyin_da</txt> <utf> 7b54 </utf>
navis-Ming-Qing_19686_0038-line-007-y1=1227-y2=1373-zone-HUMAN-x=1359-y=0071-w=0064-h=0058-ybas=0096-nink=800-segm=PERM1fwd <txt>@engl_bright_pinyin_ming</txt> <utf> 660e </utf>
navis-Ming-Qing_19686_0038-line-007-y1=1227-y2=1373-zone-HUMAN-x=1359-y=0071-w=0064-h=0064-ybas=0096-nink=923-segm=PERM1fwd <txt>@engl_bright_pinyin_ming</txt> <utf> 660e </utf>
navis-Ming-Qing_19686_0038-line-007-y1=1227-y2=1373-zone-HUMAN-x=1359-y=0072-w=0063-h=0057-ybas=0096-nink=753-segm=PERM1fwd <txt>@engl_bright_pinyin_ming</txt> <utf> 660e </utf>
navis-Ming-Qing_19686_0038-line-007-y1=1227-y2=1373-zone-HUMAN-x=1126-y=0064-w=0067-h=0065-ybas=0096-nink=676-segm=PERM1fwd <txt>@engl_foot_pinyin_zu</txt> <utf> 8db3 </utf>
navis-Ming-Qing_19686_0038-line-007-y1=1227-y2=1373-zone-HUMAN-x=1126-y=0064-w=0067-h=0065-ybas=0096-nink=737-segm=PERM1fwd <txt>@engl_foot_pinyin_zu</txt> <utf> 8db3 </utf>
navis-Ming-Qing_19686_0038-line-007-y1=1227-y2=1373-zone-HUMAN-x=1126-y=0064-w=0067-h=0080-ybas=0096-nink=807-segm=PERM1fwd <txt>@engl_foot_pinyin_zu</txt> <utf> 8db3 </utf>
navis-Ming-Qing_19686_0038-line-007-y1=1227-y2=1373-zone-HUMAN-x=2198-y=0063-w=0073-h=0066-ybas=0096-nink=830-segm=PERM1fwd <txt>@engl_linen_pinyin_bu</txt> <utf> 5e03 </utf>
navis-Ming-Qing_19686_0038-line-007-y1=1227-y2=1373-zone-HUMAN-x=2198-y=0063-w=0073-h=0066-ybas=0096-nink=884-segm=PERM1fwd <txt>@engl_linen_pinyin_bu</txt> <utf> 5e03 </utf>
navis-Ming-Qing_19686_0038-line-007-y1=1227-y2=1373-zone-HUMAN-x=2198-y=0063-w=0073-h=0069-ybas=0096-nink=977-segm=PERM1fwd <txt>@engl_linen_pinyin_bu</txt> <utf> 5e03 </utf>
navis-Ming-Qing_19686_0038-line-007-y1=1227-y2=1373-zone-HUMAN-x=1428-y=0072-w=0074-h=0057-ybas=0096-nink=955-segm=PERM1fwd <txt>@engl_morning_pinyin_chao_or_zhao</txt> <utf> 671d </utf>
navis-Ming-Qing_19686_0038-line-007-y1=1227-y2=1373-zone-HUMAN-x=1896-y=0052-w=0069-h=0077-ybas=0096-nink=632-segm=PERM1fwd <txt>@engl_rest_pinyin_xiu</txt> <utf> 4f11 </utf>
navis-Ming-Qing_19686_0038-line-007-y1=1227-y2=1373-zone-HUMAN-x=1896-y=0052-w=0069-h=0077-ybas=0096-nink=695-segm=PERM1fwd <txt>@engl_rest_pinyin_xiu</txt> <utf> 4f11 </utf>
navis-Ming-Qing_19686_0038-line-007-y1=1227-y2=1373-zone-HUMAN-x=1896-y=0052-w=0069-h=0086-ybas=0096-nink=843-segm=PERM1fwd <txt>@engl_rest_pinyin_xiu</txt> <utf> 4f11 </utf>
navis-Ming-Qing_19686_0038-line-007-y1=1227-y2=1373-zone-HUMAN-x=1660-y=0059-w=0072-h=0070-ybas=0096-nink=771-segm=PERM1fwd <txt>@engl_support_pinyin_fu</txt> <utf> 6276 </utf>
navis-Ming-Qing_19686_0038-line-007-y1=1227-y2=1373-zone-HUMAN-x=1660-y=0059-w=0073-h=0070-ybas=0096-nink=688-segm=PERM1fwd <txt>@engl_support_pinyin_fu</txt> <utf> 6276 </utf>
navis-Ming-Qing_19686_0038-line-007-y1=1227-y2=1373-zone-HUMAN-x=1660-y=0059-w=0074-h=0085-ybas=0096-nink=833-segm=PERM1fwd <txt>@engl_support_pinyin_fu</txt> <utf> 6276 </utf>
navis-Ming-Qing_19686_0038-line-007-y1=1227-y2=1373-zone-HUMAN-x=2050-y=0051-w=0065-h=0078-ybas=0096-nink=790-segm=PERM1fwd <txt>@engl_woods_pinyin_lin</txt> <utf> 6797 </utf>
navis-Ming-Qing_19686_0038-line-007-y1=1227-y2=1373-zone-HUMAN-x=2050-y=0051-w=0065-h=0078-ybas=0096-nink=861-segm=PERM1fwd <txt>@engl_woods_pinyin_lin</txt> <utf> 6797 </utf>
navis-Ming-Qing_19686_0038-line-007-y1=1227-y2=1373-zone-HUMAN-x=2050-y=0051-w=0065-h=0082-ybas=0096-nink=934-segm=PERM1fwd <txt>@engl_woods_pinyin_lin</txt> <utf> 6797 </utf>
