navis-Ming-Qing_HarvYench_18_3_2235_0033-line-006-y1=636-y2=778-zone-HUMAN-x=1910-y=0039-w=0084-h=0086-ybas=0109-nink=964-segm=PERM1fwd <txt>@engl_big_pinyin_da</txt> <utf> 5927 </utf>
navis-Ming-Qing_HarvYench_18_3_2235_0033-line-006-y1=636-y2=778-zone-HUMAN-x=1910-y=0039-w=0084-h=0086-ybas=0109-nink=964-segm=PERM1fwd <txt>@engl_big_pinyin_da</txt> <utf> 5927 </utf>
navis-Ming-Qing_HarvYench_18_3_2235_0033-line-006-y1=636-y2=778-zone-HUMAN-x=1910-y=0039-w=0084-h=0086-ybas=0109-nink=964-segm=PERM1fwd <txt>@engl_big_pinyin_da</txt> <utf> 5927 </utf>
navis-Ming-Qing_HarvYench_18_3_2235_0033-line-006-y1=636-y2=778-zone-HUMAN-x=1910-y=0039-w=0084-h=0086-ybas=0109-nink=964-segm=PERM1fwd <txt>@engl_big_pinyin_da</txt> <utf> 5927 </utf>
