navis-Ming-Qing_HarvYench_18_10_10092_0143-line-012-y1=1303-y2=1448-zone-HUMAN-x=0106-y=0043-w=0078-h=0081-ybas=0058-nink=1521-ns=1-segm=PERM4fwd <txt>@engl_and_pinyin_yu_traditional</txt> <utf> 8207 </utf>
navis-Ming-Qing_HarvYench_18_10_10092_0143-line-012-y1=1303-y2=1448-zone-HUMAN-x=0106-y=0043-w=0078-h=0081-ybas=0058-nink=1521-segm=PERM1fwd <txt>@engl_and_pinyin_yu_traditional</txt> <utf> 8207 </utf>
navis-Ming-Qing_HarvYench_18_10_10092_0143-line-012-y1=1303-y2=1448-zone-HUMAN-x=0814-y=0033-w=0050-h=0042-ybas=0058-nink=491-segm=PERM1fwd <txt>@engl_moon_pinyin_yue</txt> <utf> 6708 </utf>
