navis-Ming-Qing_HarvYench_18_10_10092_0163-line-010-y1=1040-y2=1187-zone-HUMAN-x=0323-y=0041-w=0075-h=0073-ybas=0093-nink=1246-ns=1-segm=PERM4fwd <txt>@engl_ability_pinyin_neng</txt> <utf> 80fd </utf>
navis-Ming-Qing_HarvYench_18_10_10092_0163-line-010-y1=1040-y2=1187-zone-HUMAN-x=1117-y=0050-w=0074-h=0065-ybas=0093-nink=1188-ns=1-segm=PERM1fwd <txt>@engl_moon_pinyin_yue</txt> <utf> 6708 </utf>
navis-Ming-Qing_HarvYench_18_10_10092_0163-line-010-y1=1040-y2=1187-zone-HUMAN-x=1117-y=0050-w=0074-h=0065-ybas=0093-nink=1188-ns=1-segm=PERM4fwd <txt>@engl_moon_pinyin_yue</txt> <utf> 6708 </utf>
navis-Ming-Qing_HarvYench_18_10_10092_0163-line-010-y1=1040-y2=1187-zone-HUMAN-x=1117-y=0050-w=0074-h=0065-ybas=0093-nink=1188-segm=PERM1fwd <txt>@engl_moon_pinyin_yue</txt> <utf> 6708 </utf>
navis-Ming-Qing_HarvYench_18_10_10092_0163-line-010-y1=1040-y2=1187-zone-HUMAN-x=0623-y=0037-w=0072-h=0076-ybas=0093-nink=1080-ns=1-segm=PERM4fwd <txt>@engl_sit_pinyin_zuo</txt> <utf> 5750 </utf>
navis-Ming-Qing_HarvYench_18_10_10092_0163-line-010-y1=1040-y2=1187-zone-HUMAN-x=0623-y=0037-w=0072-h=0076-ybas=0093-nink=1080-segm=PERM1fwd <txt>@engl_sit_pinyin_zuo</txt> <utf> 5750 </utf>
