navis-Ming-Qing_HarvYench_18_10_10092_0164-line-002-y1=22-y2=162-zone-HUMAN-x=1569-y=0039-w=0070-h=0073-ybas=0055-nink=1200-segm=PERM1fwd <txt>@engl_again_pinyin_you</txt> <utf> 53c8 </utf>
navis-Ming-Qing_HarvYench_18_10_10092_0164-line-002-y1=22-y2=162-zone-HUMAN-x=0165-y=0043-w=0071-h=0074-ybas=0055-nink=1334-ns=1-segm=PERM4fwd <txt>@engl_married_women_pinyin_fu</txt> <utf> 5a66 </utf>
navis-Ming-Qing_HarvYench_18_10_10092_0164-line-002-y1=22-y2=162-zone-HUMAN-x=0071-y=0049-w=0073-h=0065-ybas=0055-nink=1154-ns=1-segm=PERM4fwd <txt>@engl_middle_pinyin_zhong</txt> <utf> 4e2d </utf>
navis-Ming-Qing_HarvYench_18_10_10092_0164-line-002-y1=22-y2=162-zone-HUMAN-x=0071-y=0049-w=0073-h=0065-ybas=0055-nink=1154-segm=PERM1fwd <txt>@engl_middle_pinyin_zhong</txt> <utf> 4e2d </utf>
navis-Ming-Qing_HarvYench_18_10_10092_0164-line-002-y1=22-y2=162-zone-HUMAN-x=1101-y=0053-w=0071-h=0062-ybas=0055-nink=1205-ns=1-segm=PERM4fwd <txt>@engl_moon_pinyin_yue</txt> <utf> 6708 </utf>
navis-Ming-Qing_HarvYench_18_10_10092_0164-line-002-y1=22-y2=162-zone-HUMAN-x=1101-y=0053-w=0071-h=0062-ybas=0055-nink=1205-segm=PERM1fwd <txt>@engl_moon_pinyin_yue</txt> <utf> 6708 </utf>
navis-Ming-Qing_HarvYench_18_10_10092_0164-line-002-y1=22-y2=162-zone-HUMAN-x=1287-y=0041-w=0071-h=0073-ybas=0055-nink=1041-segm=PERM1fwd <txt>@engl_separate_pinyin_bie</txt> <utf> 522b </utf>
navis-Ming-Qing_HarvYench_18_10_10092_0164-line-002-y1=22-y2=162-zone-HUMAN-x=1945-y=0043-w=0070-h=0065-ybas=0055-nink=1102-segm=PERM1fwd <txt>@engl_towards_pinyin_xiang</txt> <utf> 5411 </utf>
navis-Ming-Qing_HarvYench_18_10_10092_0164-line-002-y1=22-y2=162-zone-HUMAN-x=2133-y=0035-w=0073-h=0073-ybas=0055-nink=1622-segm=PERM1fwd <txt>@engl_without_pinyin_wu_traditional</txt> <utf> 7121 </utf>
navis-Ming-Qing_HarvYench_18_10_10092_0164-line-002-y1=22-y2=162-zone-HUMAN-x=1756-y=0037-w=0074-h=0077-ybas=0055-nink=1236-ns=1-segm=PERM4fwd <txt>@engl_year_pinyin_nian</txt> <utf> 5e74 </utf>
navis-Ming-Qing_HarvYench_18_10_10092_0164-line-002-y1=22-y2=162-zone-HUMAN-x=1756-y=0037-w=0074-h=0077-ybas=0055-nink=1236-segm=PERM1fwd <txt>@engl_year_pinyin_nian</txt> <utf> 5e74 </utf>
