navis-Ming-Qing_HarvYench_18_10_10092_0082-line-003-y1=215-y2=350-zone-HUMAN-x=0822-y=0034-w=0072-h=0074-ybas=0072-nink=779-segm=PERM1fwd <txt>@engl_above_pinyin_shang</txt> <utf> 4E0A </utf>
navis-Ming-Qing_HarvYench_18_10_10092_0082-line-003-y1=215-y2=350-zone-HUMAN-x=0165-y=0034-w=0071-h=0072-ybas=0072-nink=1127-ns=1-segm=PERM1fwd <txt>@engl_classical_pinyin_gu</txt> <utf> 53E4 </utf>
navis-Ming-Qing_HarvYench_18_10_10092_0082-line-003-y1=215-y2=350-zone-HUMAN-x=0165-y=0034-w=0071-h=0072-ybas=0072-nink=1127-segm=PERM1fwd <txt>@engl_classical_pinyin_gu</txt> <utf> 53E4 </utf>
navis-Ming-Qing_HarvYench_18_10_10092_0082-line-003-y1=215-y2=350-zone-HUMAN-x=0165-y=0034-w=0071-h=0072-ybas=0072-nink=1127-segm=PERM4fwd <txt>@engl_classical_pinyin_gu</txt> <utf> 53E4 </utf>
navis-Ming-Qing_HarvYench_18_10_10092_0082-line-003-y1=215-y2=350-zone-HUMAN-x=1206-y=0037-w=0073-h=0072-ybas=0072-nink=976-segm=PERM1fwd <txt>@engl_people_pinyin_ren</txt> <utf> 4eba </utf>
navis-Ming-Qing_HarvYench_18_10_10092_0082-line-003-y1=215-y2=350-zone-HUMAN-x=1206-y=0037-w=0073-h=0072-ybas=0072-nink=976-segm=PERM4fwd <txt>@engl_people_pinyin_ren</txt> <utf> 4eba </utf>
navis-Ming-Qing_HarvYench_18_10_10092_0082-line-003-y1=215-y2=350-zone-HUMAN-x=0541-y=0032-w=0073-h=0073-ybas=0072-nink=1361-segm=PERM1fwd <txt>@engl_water_pinyin_shui</txt> <utf> 6c34 </utf>
navis-Ming-Qing_HarvYench_18_10_10092_0082-line-003-y1=215-y2=350-zone-HUMAN-x=0541-y=0032-w=0073-h=0073-ybas=0072-nink=1361-segm=PERM4fwd <txt>@engl_water_pinyin_shui</txt> <utf> 6c34 </utf>
